AerospaceToolbox/__init__.py
Aerospace_Toolbox-0.0.1.dist-info/LICENSE
Aerospace_Toolbox-0.0.1.dist-info/METADATA
Aerospace_Toolbox-0.0.1.dist-info/WHEEL
Aerospace_Toolbox-0.0.1.dist-info/top_level.txt
Aerospace_Toolbox-0.0.1.dist-info/RECORD
